pywin32
re
subprocess
