Metadata-Version: 2.1
Name: reshadowcode
Version: 0.0.3
Summary: For Shadow Copy research in Windows
Home-page: https://github.com/alicangnll/pyshadow
Author: Ali Can Gönüllü
License: MIT
Keywords: Windows,VSS,win32,Shadow,Copy
